fairsight
fairsight_env
