Metadata-Version: 2.4
Name: fairsight
Version: 1.0.0
Summary: Comprehensive AI Ethics and Bias Detection Toolkit with SAP Integration
Author: Abhay Pratap Singh
Author-email: Vijay K S <ksvijay2005@gmail.com>
Maintainer-email: Vijay K S <ksvijay2005@gmail.com>
License: MIT
Project-URL: Homepage, https://github.com/KS-Vijay/fairsight
Project-URL: Documentation, https://fairsight.readthedocs.io/
Project-URL: Repository, https://github.com/KS-Vijay/fairsight
Project-URL: Bug Reports, https://github.com/KS-Vijay/fairsight/issues
Project-URL: Source, https://github.com/KS-Vijay/fairsight
Keywords: ai ethics,bias detection,fairness,machine learning,audit,sap hana,explainability,responsible ai,illegal data detection,perceptual hashing,image similarity
Classifier: Development Status :: 4 - Beta
Classifier: Intended Audience :: Developers
Classifier: Intended Audience :: Science/Research
Classifier: License :: OSI Approved :: MIT License
Classifier: Operating System :: OS Independent
Classifier: Programming Language :: Python :: 3
Classifier: Programming Language :: Python :: 3.8
Classifier: Programming Language :: Python :: 3.9
Classifier: Programming Language :: Python :: 3.10
Classifier: Programming Language :: Python :: 3.11
Classifier: Topic :: Scientific/Engineering :: Artificial Intelligence
Classifier: Topic :: Software Development :: Libraries :: Python Modules
Classifier: Topic :: Software Development :: Quality Assurance
Requires-Python: >=3.8
License-File: LICENSE
Requires-Dist: pandas>=1.3.0
Requires-Dist: numpy>=1.21.0
Requires-Dist: scikit-learn>=1.0.0
Requires-Dist: shap>=0.40.0
Requires-Dist: lime>=0.2.0
Requires-Dist: matplotlib>=3.3.0
Requires-Dist: seaborn>=0.11.0
Requires-Dist: plotly>=5.0.0
Requires-Dist: markdown>=3.3.0
Requires-Dist: fpdf>=1.7.2
Requires-Dist: hdbcli>=2.15.0
Requires-Dist: scipy>=1.7.0
Requires-Dist: joblib>=1.0.0
Requires-Dist: requests>=2.25.0
Requires-Dist: Pillow>=8.0.0
Requires-Dist: imagehash>=4.3.1
Requires-Dist: torch>=1.9.0
Requires-Dist: open-clip-torch>=2.0.0
Requires-Dist: diffusers>=0.10.0
Requires-Dist: asyncio-throttle>=1.0.0
Requires-Dist: numba>=0.56.0
Requires-Dist: xgboost>=1.5.0
Requires-Dist: lightgbm>=3.0.0
Requires-Dist: catboost>=0.26.0
Provides-Extra: dev
Requires-Dist: pytest>=6.0.0; extra == "dev"
Requires-Dist: pytest-cov>=2.0.0; extra == "dev"
Requires-Dist: black>=21.0.0; extra == "dev"
Requires-Dist: flake8>=3.8.0; extra == "dev"
Requires-Dist: mypy>=0.800; extra == "dev"
Provides-Extra: docs
Requires-Dist: sphinx>=4.0; extra == "docs"
Requires-Dist: sphinx-rtd-theme>=0.5; extra == "docs"
Requires-Dist: sphinx-autodoc-typehints>=1.12; extra == "docs"
Provides-Extra: sap
Requires-Dist: hdbcli>=2.15; extra == "sap"
Requires-Dist: sap-hana>=1.0; extra == "sap"
Provides-Extra: full
Requires-Dist: jupyter>=1.0.0; extra == "full"
Requires-Dist: notebook>=6.0.0; extra == "full"
Requires-Dist: xgboost>=1.5.0; extra == "full"
Requires-Dist: lightgbm>=3.0.0; extra == "full"
Requires-Dist: catboost>=0.26.0; extra == "full"
Dynamic: license-file
